bayesian_models_loggi/__init__.py
bayesian_models_loggi/beta.py
bayesian_models_loggi-0.0.1.dist-info/METADATA
bayesian_models_loggi-0.0.1.dist-info/WHEEL
bayesian_models_loggi-0.0.1.dist-info/top_level.txt
bayesian_models_loggi-0.0.1.dist-info/RECORD
