Metadata-Version: 2.1
Name: bayesian-models-loggi
Version: 0.0.1
Summary: Bayesian Models, focused on comparing tests scenarios.
Home-page: UNKNOWN
Author: Loggi - Yan Werneck
License: MIT
Platform: UNKNOWN
Requires-Dist: numpy
Requires-Dist: plotly
